social_behavior_analysis/__init__.py
social_behavior_analysis/social_behavior_analysis.py
social_behavior_analysis_bendevlin18-0.0.1.dist-info/METADATA
social_behavior_analysis_bendevlin18-0.0.1.dist-info/WHEEL
social_behavior_analysis_bendevlin18-0.0.1.dist-info/top_level.txt
social_behavior_analysis_bendevlin18-0.0.1.dist-info/RECORD
