Metadata-Version: 2.1
Name: social-behavior-analysis-bendevlin18
Version: 0.0.1
Summary: Package to facilitate analysis of DLC social behavior output
Home-page: https://github.com/bendevlin18/social-behavior-analysis
Author: Ben Devlin 
Author-email: benjamin.devlin@duke.edu
License: UNKNOWN
Platform: UNKNOWN
Classifier: Programming Language :: Python :: 3
Classifier: License :: OSI Approved :: MIT License
Classifier: Operating System :: OS Independent
Requires-Python: >=3.6
